add_core_mop/__init__.py
add_core_mop/base_model_wrapper.py
add_core_mop/constant.py
add_core_mop/inference_wrapper.py
add_core_mop/util.py
add_core_mop-25.0.dist-info/METADATA
add_core_mop-25.0.dist-info/WHEEL
add_core_mop-25.0.dist-info/top_level.txt
add_core_mop-25.0.dist-info/RECORD
