Metadata-Version: 2.1
Name: add-core-mop
Version: 25.0
Summary: Utility SDK for RAI Model Onboarding Pipeline (MOP) model contributor.
Requires-Python: >=3.8.0
Requires-Dist: pyraisdk ~=0.3.7
Requires-Dist: PyYAML >=6.0
Requires-Dist: numpy >=1.22.0
